residual_anomaly_detector/ResidualAnomalyDetector.py
residual_anomaly_detector/__init__.py
residual_anomaly_detector/exps/StarAiFlow.py
residual_anomaly_detector/exps/__init__.py
residual_anomaly_detector/exps/io.py
residual_anomaly_detector-0.0.1.dist-info/AUTHORS.rst
residual_anomaly_detector-0.0.1.dist-info/LICENSE.txt
residual_anomaly_detector-0.0.1.dist-info/METADATA
residual_anomaly_detector-0.0.1.dist-info/WHEEL
residual_anomaly_detector-0.0.1.dist-info/top_level.txt
residual_anomaly_detector-0.0.1.dist-info/RECORD
